graphicsmilens/__init__.py
graphicsmilens/graf.py
graphicsmilens-1.1.12.dist-info/LICENSE
graphicsmilens-1.1.12.dist-info/METADATA
graphicsmilens-1.1.12.dist-info/WHEEL
graphicsmilens-1.1.12.dist-info/top_level.txt
graphicsmilens-1.1.12.dist-info/RECORD
