Metadata-Version: 2.1
Name: graphicsmilens
Version: 1.1.12
Summary: Pacote gerador de gráficos
Author: Milene Fialho
Author-email: milefialho16@gmail.com
License: MIT
License-File: LICENSE
Requires-Dist: matplotlib
Requires-Dist: pandas
